LICENSE.txt
MANIFEST.in
setup.py
dd_scenario/__init__.py
dd_scenario/asset.py
dd_scenario/base_resource.py
dd_scenario/cli.py
dd_scenario/client.py
dd_scenario/container.py
dd_scenario/model_builder.py
dd_scenario/solve.py
dd_scenario/table.py
dd_scenario.egg-info/PKG-INFO
dd_scenario.egg-info/SOURCES.txt
dd_scenario.egg-info/dependency_links.txt
dd_scenario.egg-info/requires.txt
dd_scenario.egg-info/top_level.txt