Metadata-Version: 1.0
Name: dd-scenario
Version: 0.9.0
Summary: The IBM Decision Optimization Scenario Python client
Home-page: UNKNOWN
Author: The IBM Decision Optimization on team
Author-email: UNKNOWN
License: 
